.gitignore
.travis.yml
MANIFEST.in
README.rst
bootstrap.py
buildout.cfg
setup.py
travis-4.1.x.cfg
travis-4.2.x.cfg
travis-4.3.x.cfg
travis.cfg
docs/HISTORY.txt
docs/INSTALL.txt
docs/LICENSE.GPL
docs/LICENSE.txt
src/theming/__init__.py
src/theming.toolkit.core.egg-info/PKG-INFO
src/theming.toolkit.core.egg-info/SOURCES.txt
src/theming.toolkit.core.egg-info/dependency_links.txt
src/theming.toolkit.core.egg-info/entry_points.txt
src/theming.toolkit.core.egg-info/namespace_packages.txt
src/theming.toolkit.core.egg-info/not-zip-safe
src/theming.toolkit.core.egg-info/requires.txt
src/theming.toolkit.core.egg-info/top_level.txt
src/theming/toolkit/__init__.py
src/theming/toolkit/core/__init__.py
src/theming/toolkit/core/configure.zcml
src/theming/toolkit/core/i18n.py
src/theming/toolkit/core/interfaces.py
src/theming/toolkit/core/permissions.zcml
src/theming/toolkit/core/profiles.zcml
src/theming/toolkit/core/testing.py
src/theming/toolkit/core/browser/__init__.py
src/theming/toolkit/core/browser/configure.zcml
src/theming/toolkit/core/browser/controlpanel.py
src/theming/toolkit/core/browser/interfaces.py
src/theming/toolkit/core/profiles/default/browserlayer.xml
src/theming/toolkit/core/profiles/default/controlpanel.xml
src/theming/toolkit/core/profiles/default/metadata.xml
src/theming/toolkit/core/profiles/default/registry.xml
src/theming/toolkit/core/tests/__init__.py
src/theming/toolkit/core/tests/test_controlpanel.py
src/theming/toolkit/core/tests/test_registry.py
src/theming/toolkit/core/tests/test_setup.py