Metadata-Version: 1.0
Name: theming.toolkit.core
Version: 0.1.2
Summary: Pluggable theming configuration with Diazo for Plone.
Home-page: https://github.com/propertyshelf/theming.toolkit.core
Author: Jens Krause
Author-email: jens@propertyshelf.com
License: GPL
Keywords: plone theming
Platform: UNKNOWN
Classifier: Framework :: Plone
Classifier: Programming Language :: Python
